gdstorage/__init__.py
gdstorage/apps.py
gdstorage/storage.py
gdstorage/tests.py
private_django_googledrive_storage-1.6.0.dist-info/LICENSE.txt
private_django_googledrive_storage-1.6.0.dist-info/METADATA
private_django_googledrive_storage-1.6.0.dist-info/WHEEL
private_django_googledrive_storage-1.6.0.dist-info/top_level.txt
private_django_googledrive_storage-1.6.0.dist-info/RECORD
