Metadata-Version: 2.1
Name: private-django-googledrive-storage
Version: 1.6.0
Summary: Storage implementation for Django that interacts with Google Drive
Home-page: https://github.com/ebridges/django-googledrive-storage
Download-URL: https://github.com/ebridges/django-googledrive-storage/tarball/1.6.0
Author: Gian Luca Dalla Torre (modified by Edward Bridges)
Author-email: gianluca.dallatorre@gmail.com (github@eqbridges.com)
License: LICENSE.txt
Keywords: django google drive storage googledrive
Classifier: Development Status :: 5 - Production/Stable
Classifier: Framework :: Django
Classifier: License :: OSI Approved :: BSD License
Classifier: Programming Language :: Python :: 3.6
Classifier: Programming Language :: Python :: 3.7
Classifier: Programming Language :: Python :: 3.8
Classifier: Programming Language :: Python :: 3.9
Classifier: Programming Language :: Python :: 3.10
License-File: LICENSE.txt
Requires-Dist: google-api-python-client (>=1.8.2)
Requires-Dist: google-auth (<2,>=1.28.0)
Requires-Dist: python-dateutil (>=2.5.3)
Requires-Dist: Django (>=2.2)
